dadra/__init__.py
dadra/graph_utils.py
dadra/sampling.py
dadra/utils.py
dadra-0.0.1.dist-info/LICENSE
dadra-0.0.1.dist-info/METADATA
dadra-0.0.1.dist-info/WHEEL
dadra-0.0.1.dist-info/top_level.txt
dadra-0.0.1.dist-info/RECORD
